[{
    "class": "8A",
    "type": "bad",
    "amount": 9
  }, {
    "class": "8A",
    "type": "good",
    "amount": 22
  }, {
    "class": "8A",
    "type": "average",
    "amount": 27
  }, {
    "class": "8A",
    "type": "excellent",
    "amount": 5
  }, {
    "class": "8B",
    "type": "bad",
    "amount": 17
  }, {
    "class": "8B",
    "type": "average",
    "amount": 27
  }, {
    "class": "8B",
    "type": "excellent",
    "amount": 25
  }, {
    "class": "8B",
    "type": "good",
    "amount": 30
  }, {
    "class": "8C",
    "type": "bad",
    "amount": 20
  }, {
    "class": "8C",
    "type": "average",
    "amount": 15
  }, {
    "class": "8C",
    "type": "good",
    "amount": 11
  }, {
    "class": "8C",
    "type": "excellent",
    "amount": 16
  }, {
    "class": "8D",
    "type": "excellent",
    "amount": 29
  }, {
    "class": "8D",
    "type": "bad",
    "amount": 17
  }, {
    "class": "8D",
    "type": "average",
    "amount": 6
  }, {
    "class": "8D",
    "type": "good",
    "amount": 17
  }]